AUTHORS
CHANGELOG
LICENSE
MANIFEST.in
README
README.rst
setup.cfg
setup.py
src/ckeditor/__init__.py
src/ckeditor/fields.py
src/ckeditor/models.py
src/ckeditor/tests.py
src/ckeditor/urls.py
src/ckeditor/views.py
src/ckeditor/widgets.py
src/ckeditor/management/__init__.py
src/ckeditor/management/commands/__init__.py
src/ckeditor/management/commands/generateckeditorthumbnails.py
src/ckeditor/static/ckeditor/ckeditor/CHANGES.html
src/ckeditor/static/ckeditor/ckeditor/INSTALL.html
src/ckeditor/static/ckeditor/ckeditor/LICENSE.html
src/ckeditor/static/ckeditor/ckeditor/ckeditor.js
src/ckeditor/static/ckeditor/ckeditor/ckeditor_basic.js
src/ckeditor/static/ckeditor/ckeditor/ckeditor_basic_source.js
src/ckeditor/static/ckeditor/ckeditor/ckeditor_source.js
src/ckeditor/static/ckeditor/ckeditor/config.js
src/ckeditor/static/ckeditor/ckeditor/contents.css
src/ckeditor/static/ckeditor/ckeditor/_samples/ajax.html
src/ckeditor/static/ckeditor/ckeditor/_samples/api.html
src/ckeditor/static/ckeditor/ckeditor/_samples/api_dialog.html
src/ckeditor/static/ckeditor/ckeditor/_samples/autogrow.html
src/ckeditor/static/ckeditor/ckeditor/_samples/bbcode.html
src/ckeditor/static/ckeditor/ckeditor/_samples/devtools.html
src/ckeditor/static/ckeditor/ckeditor/_samples/divreplace.html
src/ckeditor/static/ckeditor/ckeditor/_samples/enterkey.html
src/ckeditor/static/ckeditor/ckeditor/_samples/fullpage.html
src/ckeditor/static/ckeditor/ckeditor/_samples/index.html
src/ckeditor/static/ckeditor/ckeditor/_samples/jqueryadapter.html
src/ckeditor/static/ckeditor/ckeditor/_samples/output_for_flash.html
src/ckeditor/static/ckeditor/ckeditor/_samples/output_html.html
src/ckeditor/static/ckeditor/ckeditor/_samples/output_xhtml.html
src/ckeditor/static/ckeditor/ckeditor/_samples/placeholder.html
src/ckeditor/static/ckeditor/ckeditor/_samples/readonly.html
src/ckeditor/static/ckeditor/ckeditor/_samples/replacebyclass.html
src/ckeditor/static/ckeditor/ckeditor/_samples/replacebycode.html
src/xadrpy.egg-info/PKG-INFO
src/xadrpy.egg-info/SOURCES.txt
src/xadrpy.egg-info/dependency_links.txt
src/xadrpy.egg-info/not-zip-safe
src/xadrpy.egg-info/top_level.txt
