Metadata-Version: 1.0
Name: xadrpy
Version: 0.6.3
Summary: Django tool
Home-page: https://github.com/pacsee/xadrpy
Author: Csaba Palankai
Author-email: csaba.palankai@gmail.com
License: GNU GPLv3
Keywords: django
Platform: UNKNOWN
Classifier: Programming Language :: Python
Classifier: Operating System :: OS Independent
Classifier: Natural Language :: English
Classifier: License :: OSI Approved :: GNU Library or Lesser General Public License (LGPL)
Classifier: Development Status :: 3 - Alpha
Classifier: Intended Audience :: Developers
Classifier: Framework :: Django
Classifier: Topic :: Software Development :: Libraries :: Python Modules
